{"_id": "n8", "headword": "seldom"}
{"_id": "n9", "headword": "realized"}
{"_id": "n10", "headword": "charm"}
{"_id": "n11", "headword": "delicate"}
{"_id": "n12", "headword": "chin"}
{"_id": "n13", "headword": "carefully"}
{"_id": "n14", "headword": "plantation"}
{"_id": "n15", "headword": "picture"}
{"_id": "n16", "headword": "spread"}
{"_id": "n17", "headword": "lap"}
{"_id": "n18", "headword": "knee"}
{"_id": "n19", "headword": "crossed"}
{"_id": "n20", "headword": "dog"}
{"_id": "n21", "headword": "waited"}
{"_id": "n22", "headword": "dull"}
{"_id": "n23", "headword": "north"}
{"_id": "n24", "headword": "smart"}
{"_id": "n25", "headword": "straight"}
{"_id": "n26", "headword": "equally"}
{"_id": "n27", "headword": "welcome"}
{"_id": "n28", "headword": "office"}
{"_id": "n29", "headword": "start"}
{"_id": "n30", "headword": "fun"}
{"_id": "n31", "headword": "mighty"}
{"_id": "n32", "headword": "endure"}
{"_id": "n33", "headword": "chief"}
{"_id": "n34", "headword": "train"}
{"_id": "n35", "headword": "hanging"}
{"_id": "n36", "headword": "catch"}
{"_id": "n37", "headword": "grown"}
{"_id": "n38", "headword": "eight"}
{"_id": "n39", "headword": "beat"}
{"_id": "n40", "headword": "explain"}
{"_id": "n41", "headword": "weather"}
{"_id": "n42", "headword": "pink"}
{"_id": "n43", "headword": "river"}
{"_id": "n44", "headword": "middle"}
{"_id": "n45", "headword": "dust"}
{"_id": "n46", "headword": "negro"}
{"_id": "n47", "headword": "disappointment"}
{"_id": "n48", "headword": "questioned"}
{"_id": "n49", "headword": "realize"}
{"_id": "n50", "headword": "interested"}
{"_id": "n51", "headword": "beg"}
{"_id": "n52", "headword": "somehow"}
{"_id": "n53", "headword": "bowed"}
{"_id": "n54", "headword": "brow"}
{"_id": "n55", "headword": "bout"}
{"_id": "n56", "headword": "supposed"}
{"_id": "n57", "headword": "smooth"}
{"_id": "n58", "headword": "save"}
{"_id": "n59", "headword": "indignation"}
{"_id": "n60", "headword": "forgot"}
{"_id": "n61", "headword": "brown"}
{"_id": "n62", "headword": "effect"}
{"_id": "n63", "headword": "simply"}
{"_id": "n64", "headword": "aware"}
{"_id": "n65", "headword": "pair"}
{"_id": "n66", "headword": "failed"}
{"_id": "n67", "headword": "arrived"}
{"_id": "n68", "headword": "decided"}
{"_id": "n69", "headword": "accept"}
{"_id": "n70", "headword": "piece"}
{"_id": "n71", "headword": "abruptly"}
{"_id": "n72", "headword": "possessed"}
{"_id": "n73", "headword": "notion"}
{"_id": "n74", "headword": "somewhere"}
{"_id": "n75", "headword": "hide"}
{"_id": "n76", "headword": "damned"}
{"_id": "n77", "headword": "blame"}
{"_id": "n78", "headword": "excuse"}
{"_id": "n79", "headword": "shot"}
{"_id": "n80", "headword": "loving"}
{"_id": "n81", "headword": "music"}
{"_id": "n82", "headword": "gwine"}
{"_id": "n83", "headword": "assured"}
{"_id": "n84", "headword": "captain"}
{"_id": "n85", "headword": "bore"}
{"_id": "n86", "headword": "entirely"}
{"_id": "n87", "headword": "generally"}
{"_id": "n88", "headword": "twice"}
{"_id": "n89", "headword": "begin"}
{"_id": "n90", "headword": "pocket"}
{"_id": "n91", "headword": "shining"}
{"_id": "n92", "headword": "wood"}
{"_id": "n93", "headword": "joined"}
{"_id": "n94", "headword": "doan"}
{"_id": "n95", "headword": "fer"}
{"_id": "n96", "headword": "dem"}
{"_id": "n97", "headword": "higher"}
{"_id": "n98", "headword": "hill"}
{"_id": "n99", "headword": "actually"}
{"_id": "n100", "headword": "shaking"}
{"_id": "n101", "headword": "terror"}
{"_id": "n102", "headword": "bedroom"}
{"_id": "n103", "headword": "wid"}
{"_id": "n104", "headword": "breast"}
{"_id": "n105", "headword": "bringing"}
{"_id": "n106", "headword": "broad"}
{"_id": "n107", "headword": "worn"}
{"_id": "n108", "headword": "path"}
{"_id": "n109", "headword": "carry"}
{"_id": "n110", "headword": "dim"}
{"_id": "n111", "headword": "rapidly"}
{"_id": "n112", "headword": "pushed"}
{"_id": "n113", "headword": "instant"}
{"_id": "n114", "headword": "writing"}
{"_id": "n115", "headword": "important"}
{"_id": "n116", "headword": "cast"}
{"_id": "n117", "headword": "meaning"}
{"_id": "n118", "headword": "driven"}
{"_id": "n119", "headword": "silk"}
{"_id": "n120", "headword": "lamp"}
{"_id": "n121", "headword": "loud"}
{"_id": "n122", "headword": "keeping"}
{"_id": "n123", "headword": "opening"}
{"_id": "n124", "headword": "purpose"}
{"_id": "n125", "headword": "aloud"}
{"_id": "n126", "headword": "startled"}
{"_id": "n127", "headword": "difficulty"}
{"_id": "n128", "headword": "seated"}
{"_id": "n129", "headword": "draw"}
{"_id": "n130", "headword": "horror"}
{"_id": "n131", "headword": "discovered"}
{"_id": "n132", "headword": "kindly"}
{"_id": "n133", "headword": "follow"}
{"_id": "n134", "headword": "habit"}
{"_id": "n135", "headword": "gate"}
{"_id": "n136", "headword": "learned"}
{"_id": "n137", "headword": "effort"}
{"_id": "n138", "headword": "familiar"}
{"_id": "n139", "headword": "stupid"}
{"_id": "n140", "headword": "embarrassed"}
{"_id": "n141", "headword": "slight"}
{"_id": "n142", "headword": "sighed"}
{"_id": "n143", "headword": "sank"}
{"_id": "n144", "headword": "wishing"}
{"_id": "n145", "headword": "shortly"}
{"_id": "n146", "headword": "understanding"}
{"_id": "n147", "headword": "grief"}
{"_id": "n148", "headword": "join"}
{"_id": "n149", "headword": "box"}
{"_id": "n150", "headword": "proper"}
{"_id": "n151", "headword": "admit"}
{"_id": "n152", "headword": "uttered"}
{"_id": "n153", "headword": "working"}
{"_id": "n154", "headword": "terrible"}
{"_id": "n155", "headword": "torn"}
{"_id": "n156", "headword": "handkerchief"}
{"_id": "n157", "headword": "following"}
{"_id": "n158", "headword": "lower"}
{"_id": "n159", "headword": "plan"}
{"_id": "n160", "headword": "mere"}
{"_id": "n161", "headword": "perfect"}
{"_id": "n162", "headword": "miserable"}
{"_id": "n163", "headword": "managed"}
{"_id": "n164", "headword": "buried"}
{"_id": "n165", "headword": "command"}
{"_id": "n166", "headword": "stirred"}
{"_id": "n167", "headword": "satisfaction"}
{"_id": "n168", "headword": "bare"}
{"_id": "n169", "headword": "whisper"}
{"_id": "n170", "headword": "lip"}
{"_id": "n171", "headword": "youth"}
{"_id": "n172", "headword": "forever"}
{"_id": "n173", "headword": "government"}
{"_id": "n174", "headword": "fought"}
{"_id": "n175", "headword": "allow"}
{"_id": "n176", "headword": "cared"}
{"_id": "n177", "headword": "ignorant"}
{"_id": "n178", "headword": "regret"}
{"_id": "n179", "headword": "importance"}
{"_id": "n180", "headword": "later"}
{"_id": "n181", "headword": "spend"}
{"_id": "n182", "headword": "fifty"}
{"_id": "n183", "headword": "wore"}
{"_id": "n184", "headword": "conscience"}
{"_id": "n185", "headword": "attempt"}
{"_id": "n186", "headword": "silently"}
{"_id": "n187", "headword": "whenever"}
{"_id": "n188", "headword": "affair"}
{"_id": "n189", "headword": "worked"}
{"_id": "n190", "headword": "existence"}
{"_id": "n191", "headword": "arrival"}
{"_id": "n192", "headword": "rough"}
{"_id": "n193", "headword": "speech"}
{"_id": "n194", "headword": "dignity"}
{"_id": "n195", "headword": "otherwise"}
{"_id": "n196", "headword": "advantage"}
{"_id": "n197", "headword": "whut"}
{"_id": "n198", "headword": "manage"}
{"_id": "n199", "headword": "ordered"}
{"_id": "n200", "headword": "gently"}
{"_id": "n201", "headword": "information"}
{"_id": "n202", "headword": "addressed"}
{"_id": "n203", "headword": "brief"}
{"_id": "n204", "headword": "approached"}
{"_id": "n205", "headword": "iron"}
{"_id": "n206", "headword": "lace"}
{"_id": "n207", "headword": "bred"}
{"_id": "n208", "headword": "sought"}
{"_id": "n209", "headword": "drawn"}
{"_id": "n210", "headword": "act"}
{"_id": "n211", "headword": "whatever"}
{"_id": "n212", "headword": "complete"}
{"_id": "n213", "headword": "property"}
{"_id": "n214", "headword": "credit"}
{"_id": "n215", "headword": "absence"}
{"_id": "n216", "headword": "usually"}
{"_id": "n217", "headword": "outside"}
{"_id": "n218", "headword": "declared"}
{"_id": "n219", "headword": "sorrow"}
{"_id": "n220", "headword": "listening"}
{"_id": "n221", "headword": "group"}
{"_id": "n222", "headword": "muttered"}
{"_id": "n223", "headword": "entrance"}
{"_id": "n224", "headword": "wear"}
{"_id": "n225", "headword": "lovely"}
{"_id": "n226", "headword": "paper"}
{"_id": "n227", "headword": "force"}
{"_id": "n228", "headword": "empty"}
{"_id": "n229", "headword": "break"}
{"_id": "n230", "headword": "acted"}
{"_id": "n231", "headword": "aid"}
{"_id": "n232", "headword": "somewhat"}
{"_id": "n233", "headword": "lit"}
{"_id": "n234", "headword": "pause"}
{"_id": "n235", "headword": "wine"}
{"_id": "n236", "headword": "today"}
{"_id": "n237", "headword": "absolutely"}
{"_id": "n238", "headword": "wuz"}
{"_id": "n239", "headword": "hurry"}
{"_id": "n240", "headword": "grow"}
{"_id": "n241", "headword": "placed"}
{"_id": "n242", "headword": "dozen"}
{"_id": "n243", "headword": "foolish"}
{"_id": "n244", "headword": "escape"}
{"_id": "n245", "headword": "forgive"}
{"_id": "n246", "headword": "showing"}
{"_id": "n247", "headword": "leaned"}
{"_id": "n248", "headword": "passion"}
{"_id": "n249", "headword": "charge"}
{"_id": "n250", "headword": "flesh"}
{"_id": "n251", "headword": "smoke"}
{"_id": "n252", "headword": "burning"}
{"_id": "n253", "headword": "fault"}
{"_id": "n254", "headword": "rushed"}
{"_id": "n255", "headword": "someone"}
{"_id": "n256", "headword": "coat"}
{"_id": "n257", "headword": "swept"}
{"_id": "n258", "headword": "buggy"}
{"_id": "n259", "headword": "touched"}
{"_id": "n260", "headword": "bread"}
{"_id": "n261", "headword": "receive"}
{"_id": "n262", "headword": "fallen"}
{"_id": "n263", "headword": "particular"}
{"_id": "n264", "headword": "relief"}
{"_id": "n265", "headword": "church"}
{"_id": "n266", "headword": "moving"}
{"_id": "n267", "headword": "remarked"}
{"_id": "n268", "headword": "hearth"}
{"_id": "n269", "headword": "trembling"}
{"_id": "n270", "headword": "mustn"}
{"_id": "n271", "headword": "pressed"}
{"_id": "n272", "headword": "greater"}
{"_id": "n273", "headword": "noise"}
{"_id": "n274", "headword": "kill"}
{"_id": "n275", "headword": "private"}
{"_id": "n276", "headword": "suffer"}
{"_id": "n277", "headword": "lonely"}
{"_id": "n278", "headword": "nurse"}
{"_id": "n279", "headword": "village"}
{"_id": "n280", "headword": "railroad"}
{"_id": "n281", "headword": "journey"}
{"_id": "n282", "headword": "farther"}
{"_id": "n283", "headword": "leaning"}
{"_id": "n284", "headword": "dirty"}
{"_id": "n285", "headword": "share"}
{"_id": "n286", "headword": "remark"}
{"_id": "n287", "headword": "trust"}
{"_id": "n288", "headword": "demanded"}
{"_id": "n289", "headword": "choice"}
{"_id": "n290", "headword": "bid"}
{"_id": "n291", "headword": "weary"}
{"_id": "n292", "headword": "frame"}
{"_id": "n293", "headword": "moon"}
{"_id": "n294", "headword": "assure"}
{"_id": "n295", "headword": "equal"}
{"_id": "n296", "headword": "pardon"}
{"_id": "n297", "headword": "taste"}
{"_id": "n298", "headword": "warn"}
{"_id": "n299", "headword": "enemy"}
{"_id": "n300", "headword": "formed"}
{"_id": "n301", "headword": "stone"}
{"_id": "n302", "headword": "intention"}
{"_id": "n303", "headword": "particularly"}
{"_id": "n304", "headword": "convinced"}
{"_id": "n305", "headword": "prepared"}
{"_id": "n306", "headword": "avoid"}
{"_id": "n307", "headword": "directly"}
{"_id": "n308", "headword": "glanced"}
{"_id": "n309", "headword": "allowed"}
{"_id": "n310", "headword": "inquired"}
{"_id": "n311", "headword": "sensible"}
{"_id": "n312", "headword": "heaven"}
{"_id": "n313", "headword": "study"}
{"_id": "n314", "headword": "reception"}
{"_id": "n315", "headword": "amiable"}
{"_id": "n316", "headword": "agreeable"}
{"_id": "n317", "headword": "obliged"}
{"_id": "n318", "headword": "honour"}
{"_id": "n319", "headword": "parlour"}
{"_id": "n320", "headword": "consequence"}
{"_id": "n321", "headword": "unavailable"}
{"_id": "n322", "headword": "behaviour"}
